pcbmodezero/__init__.py
pcbmodezero/components/__init__.py
pcbmodezero/components/led-1206.svg
pcbmodezero/components/leds.py
pcbmodezero/components/vias.py
pcbmodezero/components/json/0805-cap.json
pcbmodezero/components/json/0805-led.json
pcbmodezero/components/json/0805.json
pcbmodezero/components/json/0p5mm-drill.json
pcbmodezero/components/json/0p8mm-drill.json
pcbmodezero/components/json/10mm-led.json
pcbmodezero/components/json/1206.json
pcbmodezero/components/json/1206_oneside.json
pcbmodezero/components/json/13mmspeaker.json
pcbmodezero/components/json/14pin-ic-dip.json
pcbmodezero/components/json/1mm-drill.json
pcbmodezero/components/json/1p5mm-plated-hole.json
pcbmodezero/components/json/1x10-2p54mm-header-stag.json
pcbmodezero/components/json/1x12-2p54mm-header-stag.json
pcbmodezero/components/json/1x12-2p54mm-ra-socket-stag.json
pcbmodezero/components/json/1x16-2p54.json
pcbmodezero/components/json/1x16-2p54mm-header-stag.json
pcbmodezero/components/json/1x4-2p54-stag.json
pcbmodezero/components/json/1x4-2p54.json
pcbmodezero/components/json/1x5-2p54.json
pcbmodezero/components/json/1x6-2p54-stag.json
pcbmodezero/components/json/1x6-2p54.json
pcbmodezero/components/json/1x6-2p54mm-header.json
pcbmodezero/components/json/1x8-2p54-header-long-pads.json
pcbmodezero/components/json/1x8-2p54-header.json
pcbmodezero/components/json/1x8-2p54mm-header-stag.json
pcbmodezero/components/json/1x9-2p54mm-smd.json
pcbmodezero/components/json/2mm-plated-hole.json
pcbmodezero/components/json/2mm5tantalum.json
pcbmodezero/components/json/2p5mm-drill.json
pcbmodezero/components/json/2way_header_pin.json
pcbmodezero/components/json/3mm-drill.json
pcbmodezero/components/json/3mm-led-flat.json
pcbmodezero/components/json/3mmLED.json
pcbmodezero/components/json/3way_header_pin.json
pcbmodezero/components/json/4mmelectro.json
pcbmodezero/components/json/555-SOIC8.json
pcbmodezero/components/json/555.json
pcbmodezero/components/json/5mm-led.json
pcbmodezero-0.0.2.dist-info/METADATA
pcbmodezero-0.0.2.dist-info/WHEEL
pcbmodezero-0.0.2.dist-info/top_level.txt
pcbmodezero-0.0.2.dist-info/RECORD
