Metadata-Version: 2.1
Name: pcbmodezero
Version: 0.0.2
Summary: Python frontend to PCBmodE
Home-page: https://github.com/TheBubbleworks/python-pcbmode-zero/
Author: Wayne Keenan
Author-email: wayne@thebubbleworks.com
Maintainer: Wayne Keenan
Maintainer-email: wayne@thebubbleworks.com
License: MIT
Platform: Windows
Platform: Linux
Platform: MacOS
Classifier: Development Status :: 2 - Pre-Alpha
Classifier: Operating System :: POSIX
Classifier: Operating System :: MacOS
Classifier: Operating System :: Microsoft :: Windows
Classifier: Programming Language :: Python :: 3
Classifier: Programming Language :: Python :: 2
Classifier: Environment :: Console
Classifier: Intended Audience :: End Users/Desktop
Requires-Dist: pcbmode
Requires-Dist: jsontree
Requires-Dist: svgwrite
Requires-Dist: svgpathtools
